milomcint/__init__.py
milomcint/modulo2.py
milomcint-0.1.0.dist-info/METADATA
milomcint-0.1.0.dist-info/WHEEL
milomcint-0.1.0.dist-info/top_level.txt
milomcint-0.1.0.dist-info/RECORD
