Metadata-Version: 2.1
Name: milomcint
Version: 0.1.0
Summary: Libreria de integracion por montecarlo
Home-page: https://gitlab.com/camilo.londonov
Author: Milo
Author-email: camilo.londonov@udea.edu.co
License: MIT
Platform: UNKNOWN
Requires-Python: >=3.10.12
Requires-Dist: matplotlib (==3.8.1)
Requires-Dist: numpy (==1.26.1)
Requires-Dist: sympy (==1.12)
